going/__init__.py
going-0.1.1.dist-info/METADATA
going-0.1.1.dist-info/WHEEL
going-0.1.1.dist-info/RECORD
